potentials/Settings.py
potentials/VERSION
potentials/__init__.py
potentials/Database/__init__.py
potentials/Database/_action.py
potentials/Database/_citation.py
potentials/Database/_faq.py
potentials/Database/_kim_potential.py
potentials/Database/_lammps_potential.py
potentials/Database/_potential.py
potentials/Database/_record.py
potentials/Database/_related_models.py
potentials/Database/_request.py
potentials/Database/_widgets.py
potentials/Database/load_database.py
potentials/buildrecord/__init__.py
potentials/buildrecord/build_lammps_potential.py
potentials/buildrecord/potential_LAMMPS/EamBuilder.py
potentials/buildrecord/potential_LAMMPS/EimBuilder.py
potentials/buildrecord/potential_LAMMPS/KimBuilder.py
potentials/buildrecord/potential_LAMMPS/LibParamBuilder.py
potentials/buildrecord/potential_LAMMPS/PairBuilder.py
potentials/buildrecord/potential_LAMMPS/ParamFileBuilder.py
potentials/buildrecord/potential_LAMMPS/PotentialLAMMPSBuilder.py
potentials/buildrecord/potential_LAMMPS/__init__.py
potentials/paramfile/ADP.py
potentials/paramfile/EAM.py
potentials/paramfile/EAMAlloy.py
potentials/paramfile/EAMFS.py
potentials/paramfile/EAMX.py
potentials/paramfile/__init__.py
potentials/paramfile/converters.py
potentials/paramfile/load_eam.py
potentials/paramfile/Tersoff/__init__.py
potentials/paramfile/Tersoff/_abop.py
potentials/record/Action.py
potentials/record/Artifact.py
potentials/record/AtomInfo.py
potentials/record/BasePotentialLAMMPS.py
potentials/record/Citation.py
potentials/record/CommandLine.py
potentials/record/FAQ.py
potentials/record/Implementation.py
potentials/record/Link.py
potentials/record/Parameter.py
potentials/record/Potential.py
potentials/record/PotentialInfo.py
potentials/record/PotentialLAMMPS.py
potentials/record/PotentialLAMMPSKIM.py
potentials/record/Request.py
potentials/record/__init__.py
potentials/tools/__init__.py
potentials/tools/atomic_info.py
potentials/tools/atomicdata.csv
potentials/tools/numderivative.py
potentials-0.4.1.dist-info/licenses/LICENSE.TXT
potentials-0.4.1.dist-info/METADATA
potentials-0.4.1.dist-info/WHEEL
potentials-0.4.1.dist-info/top_level.txt
potentials-0.4.1.dist-info/RECORD
