Metadata-Version: 2.4
Name: potentials
Version: 0.4.1
Summary: API database tools for accessing the NIST Interatomic Potentials Repository: explore and download interatomic potentials and computed properties.
Home-page: https://github.com/usnistgov/potentials
Author: Lucas Hale
Author-email: lucas.hale@nist.gov
Keywords: atom,atomic,atomistic,molecular dynamics,interatomic potential,force field
Classifier: Development Status :: 4 - Beta
Classifier: Intended Audience :: Science/Research
Classifier: Natural Language :: English
Classifier: Programming Language :: Python :: 3.8
Classifier: Programming Language :: Python :: 3.9
Classifier: Programming Language :: Python :: 3.10
Classifier: Programming Language :: Python :: 3.11
Classifier: Topic :: Scientific/Engineering :: Physics
License-File: LICENSE.TXT
Requires-Dist: xmltodict
Requires-Dist: DataModelDict
Requires-Dist: unidecode
Requires-Dist: numpy
Requires-Dist: matplotlib
Requires-Dist: pandas
Requires-Dist: requests
Requires-Dist: habanero
Requires-Dist: bibtexparser
Requires-Dist: ipywidgets
Requires-Dist: cdcs
Requires-Dist: yabadaba>=0.3.1
Dynamic: author
Dynamic: author-email
Dynamic: classifier
Dynamic: description
Dynamic: home-page
Dynamic: keywords
Dynamic: license-file
Dynamic: requires-dist
Dynamic: summary
